{"slug":"lion-energy-100w-lion-energy-2-solar-panels-0-emp-bags-0-led-light-st","series":[{"offerId":"0bb6e032-a61d-4489-bee0-ccc20cfcfb75","retailerName":"Shop Solar Kits","retailerSlug":"shop-solar-kits","points":[{"date":"2026-03-23","priceCents":212600,"inStock":true}]},{"offerId":"850ddc36-c9fd-4519-917b-7f0aaf5402fd","retailerName":"Shop Solar Kits","retailerSlug":"shop-solar-kits","points":[{"date":"2026-03-23","priceCents":342500,"inStock":true}]}],"lowestAvailable":[{"date":"2026-03-23","priceCents":212600}]}